{
    "Version": "1.1",
    "Data": {
        "Source": "e:\\my_work\\directx 11\\sculpt\\userinterface\\gpu_shadertypes.hpp",
        "ProvidedModule": "",
        "Includes": [
            "c:\\program files (x86)\\windows kits\\10\\include\\10.0.19041.0\\um\\directxmath.h",
            "c:\\program files (x86)\\windows kits\\10\\include\\10.0.19041.0\\ucrt\\math.h",
            "c:\\program files (x86)\\windows kits\\10\\include\\10.0.19041.0\\ucrt\\corecrt_math.h",
            "c:\\program files (x86)\\windows kits\\10\\include\\10.0.19041.0\\ucrt\\corecrt.h",
            "d:\\programs\\vs 19\\vc\\tools\\msvc\\14.29.30133\\include\\vcruntime.h",
            "d:\\programs\\vs 19\\vc\\tools\\msvc\\14.29.30133\\include\\sal.h",
            "d:\\programs\\vs 19\\vc\\tools\\msvc\\14.29.30133\\include\\concurrencysal.h",
            "d:\\programs\\vs 19\\vc\\tools\\msvc\\14.29.30133\\include\\vadefs.h",
            "c:\\program files (x86)\\windows kits\\10\\include\\10.0.19041.0\\ucrt\\float.h",
            "d:\\programs\\vs 19\\vc\\tools\\msvc\\14.29.30133\\include\\intrin.h",
            "d:\\programs\\vs 19\\vc\\tools\\msvc\\14.29.30133\\include\\intrin0.inl.h",
            "d:\\programs\\vs 19\\vc\\tools\\msvc\\14.29.30133\\include\\setjmp.h",
            "d:\\programs\\vs 19\\vc\\tools\\msvc\\14.29.30133\\include\\immintrin.h",
            "d:\\programs\\vs 19\\vc\\tools\\msvc\\14.29.30133\\include\\wmmintrin.h",
            "d:\\programs\\vs 19\\vc\\tools\\msvc\\14.29.30133\\include\\nmmintrin.h",
            "d:\\programs\\vs 19\\vc\\tools\\msvc\\14.29.30133\\include\\smmintrin.h",
            "d:\\programs\\vs 19\\vc\\tools\\msvc\\14.29.30133\\include\\tmmintrin.h",
            "d:\\programs\\vs 19\\vc\\tools\\msvc\\14.29.30133\\include\\pmmintrin.h",
            "d:\\programs\\vs 19\\vc\\tools\\msvc\\14.29.30133\\include\\emmintrin.h",
            "d:\\programs\\vs 19\\vc\\tools\\msvc\\14.29.30133\\include\\xmmintrin.h",
            "d:\\programs\\vs 19\\vc\\tools\\msvc\\14.29.30133\\include\\mmintrin.h",
            "c:\\program files (x86)\\windows kits\\10\\include\\10.0.19041.0\\ucrt\\malloc.h",
            "c:\\program files (x86)\\windows kits\\10\\include\\10.0.19041.0\\ucrt\\corecrt_malloc.h",
            "d:\\programs\\vs 19\\vc\\tools\\msvc\\14.29.30133\\include\\zmmintrin.h",
            "d:\\programs\\vs 19\\vc\\tools\\msvc\\14.29.30133\\include\\ammintrin.h",
            "c:\\program files (x86)\\windows kits\\10\\include\\10.0.19041.0\\ucrt\\assert.h",
            "d:\\programs\\vs 19\\vc\\tools\\msvc\\14.29.30133\\include\\stdint.h",
            "c:\\program files (x86)\\windows kits\\10\\include\\10.0.19041.0\\um\\directxmathconvert.inl",
            "c:\\program files (x86)\\windows kits\\10\\include\\10.0.19041.0\\um\\directxmathvector.inl",
            "c:\\program files (x86)\\windows kits\\10\\include\\10.0.19041.0\\um\\directxmathmatrix.inl",
            "c:\\program files (x86)\\windows kits\\10\\include\\10.0.19041.0\\um\\directxmathmisc.inl",
            "e:\\my_work\\directx 11\\sculpt\\userinterface\\thirdparty\\glm\\glm\\vec2.hpp",
            "e:\\my_work\\directx 11\\sculpt\\userinterface\\thirdparty\\glm\\glm\\ext\\vector_bool2.hpp",
            "e:\\my_work\\directx 11\\sculpt\\userinterface\\thirdparty\\glm\\glm\\detail\\type_vec2.hpp",
            "e:\\my_work\\directx 11\\sculpt\\userinterface\\thirdparty\\glm\\glm\\detail\\qualifier.hpp",
            "e:\\my_work\\directx 11\\sculpt\\userinterface\\thirdparty\\glm\\glm\\detail\\setup.hpp",
            "d:\\programs\\vs 19\\vc\\tools\\msvc\\14.29.30133\\include\\cassert",
            "d:\\programs\\vs 19\\vc\\tools\\msvc\\14.29.30133\\include\\yvals_core.h",
            "d:\\programs\\vs 19\\vc\\tools\\msvc\\14.29.30133\\include\\xkeycheck.h",
            "c:\\program files (x86)\\windows kits\\10\\include\\10.0.19041.0\\ucrt\\assert.h",
            "d:\\programs\\vs 19\\vc\\tools\\msvc\\14.29.30133\\include\\cstddef",
            "c:\\program files (x86)\\windows kits\\10\\include\\10.0.19041.0\\ucrt\\stddef.h",
            "d:\\programs\\vs 19\\vc\\tools\\msvc\\14.29.30133\\include\\xtr1common",
            "e:\\my_work\\directx 11\\sculpt\\userinterface\\thirdparty\\glm\\glm\\simd\\platform.h",
            "d:\\programs\\vs 19\\vc\\tools\\msvc\\14.29.30133\\include\\cstdint",
            "d:\\programs\\vs 19\\vc\\tools\\msvc\\14.29.30133\\include\\type_traits",
            "d:\\programs\\vs 19\\vc\\tools\\msvc\\14.29.30133\\include\\xstddef",
            "d:\\programs\\vs 19\\vc\\tools\\msvc\\14.29.30133\\include\\cstdlib",
            "c:\\program files (x86)\\windows kits\\10\\include\\10.0.19041.0\\ucrt\\math.h",
            "c:\\program files (x86)\\windows kits\\10\\include\\10.0.19041.0\\ucrt\\stdlib.h",
            "c:\\program files (x86)\\windows kits\\10\\include\\10.0.19041.0\\ucrt\\corecrt_search.h",
            "c:\\program files (x86)\\windows kits\\10\\include\\10.0.19041.0\\ucrt\\corecrt_wstdlib.h",
            "d:\\programs\\vs 19\\vc\\tools\\msvc\\14.29.30133\\include\\limits.h",
            "d:\\programs\\vs 19\\vc\\tools\\msvc\\14.29.30133\\include\\initializer_list",
            "e:\\my_work\\directx 11\\sculpt\\userinterface\\thirdparty\\glm\\glm\\detail\\type_vec2.inl",
            "e:\\my_work\\directx 11\\sculpt\\userinterface\\thirdparty\\glm\\glm\\detail\\compute_vector_relational.hpp",
            "e:\\my_work\\directx 11\\sculpt\\userinterface\\thirdparty\\glm\\glm\\detail\\setup.hpp",
            "d:\\programs\\vs 19\\vc\\tools\\msvc\\14.29.30133\\include\\limits",
            "d:\\programs\\vs 19\\vc\\tools\\msvc\\14.29.30133\\include\\cfloat",
            "d:\\programs\\vs 19\\vc\\tools\\msvc\\14.29.30133\\include\\climits",
            "d:\\programs\\vs 19\\vc\\tools\\msvc\\14.29.30133\\include\\cwchar",
            "d:\\programs\\vs 19\\vc\\tools\\msvc\\14.29.30133\\include\\cstdio",
            "c:\\program files (x86)\\windows kits\\10\\include\\10.0.19041.0\\ucrt\\stdio.h",
            "c:\\program files (x86)\\windows kits\\10\\include\\10.0.19041.0\\ucrt\\corecrt_wstdio.h",
            "c:\\program files (x86)\\windows kits\\10\\include\\10.0.19041.0\\ucrt\\corecrt_stdio_config.h",
            "c:\\program files (x86)\\windows kits\\10\\include\\10.0.19041.0\\ucrt\\wchar.h",
            "c:\\program files (x86)\\windows kits\\10\\include\\10.0.19041.0\\ucrt\\corecrt_memcpy_s.h",
            "c:\\program files (x86)\\windows kits\\10\\include\\10.0.19041.0\\ucrt\\errno.h",
            "d:\\programs\\vs 19\\vc\\tools\\msvc\\14.29.30133\\include\\vcruntime_string.h",
            "c:\\program files (x86)\\windows kits\\10\\include\\10.0.19041.0\\ucrt\\corecrt_wconio.h",
            "c:\\program files (x86)\\windows kits\\10\\include\\10.0.19041.0\\ucrt\\corecrt_wctype.h",
            "c:\\program files (x86)\\windows kits\\10\\include\\10.0.19041.0\\ucrt\\corecrt_wdirect.h",
            "c:\\program files (x86)\\windows kits\\10\\include\\10.0.19041.0\\ucrt\\corecrt_wio.h",
            "c:\\program files (x86)\\windows kits\\10\\include\\10.0.19041.0\\ucrt\\corecrt_share.h",
            "c:\\program files (x86)\\windows kits\\10\\include\\10.0.19041.0\\ucrt\\corecrt_wprocess.h",
            "c:\\program files (x86)\\windows kits\\10\\include\\10.0.19041.0\\ucrt\\corecrt_wstring.h",
            "c:\\program files (x86)\\windows kits\\10\\include\\10.0.19041.0\\ucrt\\corecrt_wtime.h",
            "c:\\program files (x86)\\windows kits\\10\\include\\10.0.19041.0\\ucrt\\sys\\stat.h",
            "c:\\program files (x86)\\windows kits\\10\\include\\10.0.19041.0\\ucrt\\sys\\types.h",
            "d:\\programs\\vs 19\\vc\\tools\\msvc\\14.29.30133\\include\\intrin0.h",
            "d:\\programs\\vs 19\\vc\\tools\\msvc\\14.29.30133\\include\\isa_availability.h",
            "e:\\my_work\\directx 11\\sculpt\\userinterface\\thirdparty\\glm\\glm\\ext\\vector_bool2_precision.hpp",
            "e:\\my_work\\directx 11\\sculpt\\userinterface\\thirdparty\\glm\\glm\\ext\\vector_float2.hpp",
            "e:\\my_work\\directx 11\\sculpt\\userinterface\\thirdparty\\glm\\glm\\ext\\vector_float2_precision.hpp",
            "e:\\my_work\\directx 11\\sculpt\\userinterface\\thirdparty\\glm\\glm\\ext\\vector_double2.hpp",
            "e:\\my_work\\directx 11\\sculpt\\userinterface\\thirdparty\\glm\\glm\\ext\\vector_double2_precision.hpp",
            "e:\\my_work\\directx 11\\sculpt\\userinterface\\thirdparty\\glm\\glm\\ext\\vector_int2.hpp",
            "e:\\my_work\\directx 11\\sculpt\\userinterface\\thirdparty\\glm\\glm\\ext\\vector_int2_sized.hpp",
            "e:\\my_work\\directx 11\\sculpt\\userinterface\\thirdparty\\glm\\glm\\ext\\scalar_int_sized.hpp",
            "e:\\my_work\\directx 11\\sculpt\\userinterface\\thirdparty\\glm\\glm\\detail\\setup.hpp",
            "e:\\my_work\\directx 11\\sculpt\\userinterface\\thirdparty\\glm\\glm\\ext\\vector_uint2.hpp",
            "e:\\my_work\\directx 11\\sculpt\\userinterface\\thirdparty\\glm\\glm\\ext\\vector_uint2_sized.hpp",
            "e:\\my_work\\directx 11\\sculpt\\userinterface\\thirdparty\\glm\\glm\\ext\\scalar_uint_sized.hpp",
            "e:\\my_work\\directx 11\\sculpt\\userinterface\\thirdparty\\glm\\glm\\detail\\setup.hpp",
            "e:\\my_work\\directx 11\\sculpt\\userinterface\\thirdparty\\glm\\glm\\vec4.hpp",
            "e:\\my_work\\directx 11\\sculpt\\userinterface\\thirdparty\\glm\\glm\\ext\\vector_bool4.hpp",
            "e:\\my_work\\directx 11\\sculpt\\userinterface\\thirdparty\\glm\\glm\\detail\\type_vec4.hpp",
            "e:\\my_work\\directx 11\\sculpt\\userinterface\\thirdparty\\glm\\glm\\detail\\type_vec4.inl",
            "e:\\my_work\\directx 11\\sculpt\\userinterface\\thirdparty\\glm\\glm\\ext\\vector_bool4_precision.hpp",
            "e:\\my_work\\directx 11\\sculpt\\userinterface\\thirdparty\\glm\\glm\\ext\\vector_float4.hpp",
            "e:\\my_work\\directx 11\\sculpt\\userinterface\\thirdparty\\glm\\glm\\ext\\vector_float4_precision.hpp",
            "e:\\my_work\\directx 11\\sculpt\\userinterface\\thirdparty\\glm\\glm\\ext\\vector_double4.hpp",
            "e:\\my_work\\directx 11\\sculpt\\userinterface\\thirdparty\\glm\\glm\\ext\\vector_double4_precision.hpp",
            "e:\\my_work\\directx 11\\sculpt\\userinterface\\thirdparty\\glm\\glm\\detail\\setup.hpp",
            "e:\\my_work\\directx 11\\sculpt\\userinterface\\thirdparty\\glm\\glm\\ext\\vector_int4.hpp",
            "e:\\my_work\\directx 11\\sculpt\\userinterface\\thirdparty\\glm\\glm\\ext\\vector_int4_sized.hpp",
            "e:\\my_work\\directx 11\\sculpt\\userinterface\\thirdparty\\glm\\glm\\ext\\vector_uint4.hpp",
            "e:\\my_work\\directx 11\\sculpt\\userinterface\\thirdparty\\glm\\glm\\ext\\vector_uint4_sized.hpp"
        ],
        "ImportedModules": [],
        "ImportedHeaderUnits": []
    }
}